app/__init__.py
app/image_injector.py
zarf_image_injector-1.0.dist-info/LICENSE
zarf_image_injector-1.0.dist-info/METADATA
zarf_image_injector-1.0.dist-info/WHEEL
zarf_image_injector-1.0.dist-info/entry_points.txt
zarf_image_injector-1.0.dist-info/top_level.txt
zarf_image_injector-1.0.dist-info/RECORD
