Metadata-Version: 2.2
Name: zarf_image_injector
Version: 1.0
Summary: This does dynamic image discovery for the zarf CD pipeline
Author-email: Andrew Robbins <ncvarsity3@gmail.com>
License: Copyright (c) 2018 The Python Packaging Authority
Keywords: zarf,image,injector
Classifier: Programming Language :: Python :: 3
Classifier: Operating System :: OS Independent
Classifier: License :: OSI Approved :: MIT License
Requires-Python: >=3.8
License-File: LICENSE
Requires-Dist: pyyaml
